LICENSE
README.md
setup.py
aliyun_log_cli.egg-info/PKG-INFO
aliyun_log_cli.egg-info/SOURCES.txt
aliyun_log_cli.egg-info/dependency_links.txt
aliyun_log_cli.egg-info/entry_points.txt
aliyun_log_cli.egg-info/requires.txt
aliyun_log_cli.egg-info/top_level.txt
aliyunlogcli/__init__.py
aliyunlogcli/cli.py
aliyunlogcli/cli_core.py
aliyunlogcli/config.py
aliyunlogcli/exceptions.py
aliyunlogcli/parser.py
aliyunlogcli/version.py
tests/test_cli.py
tests/test_cmd_format.py
tests/test_error_message.py