Metadata-Version: 2.4
Name: aliyun-log-cli
Version: 0.2.10
Summary: Aliyun log service CLI
Home-page: https://github.com/aliyun/aliyun-log-cli
Author: Aliyun
Classifier: Development Status :: 4 - Beta
Classifier: License :: OSI Approved :: MIT License
Classifier: Operating System :: OS Independent
Classifier: Programming Language :: Python :: 2.6
Classifier: Programming Language :: Python :: 2.7
Classifier: Programming Language :: Python :: 3.3
Classifier: Programming Language :: Python :: 3.4
Classifier: Programming Language :: Python :: 3.5
Classifier: Programming Language :: Python :: 3.6
Classifier: Programming Language :: Python :: 3.7
Classifier: Programming Language :: Python :: Implementation :: PyPy
License-File: LICENSE
Requires-Dist: jmespath
Requires-Dist: docopt
Requires-Dist: requests
Requires-Dist: aliyun-python-sdk-core
Requires-Dist: aliyun-python-sdk-sts
Requires-Dist: aliyun-log-python-sdk<0.10.0,>=0.8.11
Dynamic: author
Dynamic: classifier
Dynamic: description
Dynamic: home-page
Dynamic: license-file
Dynamic: requires-dist
Dynamic: summary
